Metadata-Version: 2.4
Name: elastic-kernel
Version: 0.1.0
Summary: An IPython Kernel that automatically saves and restores Jupyter Notebook execution states.
Author-email: ryutarom <m2002r1028@icloud.com>
License:                                  Apache License
Project-URL: Homepage, https://github.com/MRyutaro/ElasticKernel
Project-URL: Repository, https://github.com/MRyutaro/ElasticKernel
Project-URL: Documentation, https://github.com/MRyutaro/ElasticKernel
Project-URL: Bug Tracker, https://github.com/MRyutaro/ElasticKernel/issues
Keywords: jupyter,kernel,elastic,checkpoint,dependency-tracking
Classifier: Development Status :: 4 - Beta
Classifier: Intended Audience :: Developers
Classifier: Intended Audience :: Science/Research
Classifier: License :: OSI Approved :: Apache Software License
Classifier: Operating System :: OS Independent
Classifier: Programming Language :: Python :: 3
Classifier: Programming Language :: Python :: 3.6
Classifier: Programming Language :: Python :: 3.7
Classifier: Programming Language :: Python :: 3.8
Classifier: Programming Language :: Python :: 3.9
Classifier: Programming Language :: Python :: 3.10
Classifier: Programming Language :: Python :: 3.11
Classifier: Topic :: Scientific/Engineering
Classifier: Topic :: Software Development
Classifier: Framework :: Jupyter
Requires-Python: >=3.6
License-File: LICENSE
Requires-Dist: dill
Requires-Dist: ipykernel
Requires-Dist: ipython
Requires-Dist: lightgbm
Requires-Dist: matplotlib
Requires-Dist: networkx
Requires-Dist: numpy
Requires-Dist: pandas
Requires-Dist: scipy
Requires-Dist: seaborn
Requires-Dist: torch
Requires-Dist: xxhash
Requires-Dist: jupyter_client
Requires-Dist: jupyter
Provides-Extra: dev
Requires-Dist: black; extra == "dev"
Requires-Dist: flake8; extra == "dev"
Requires-Dist: isort; extra == "dev"
Requires-Dist: mypy; extra == "dev"
Requires-Dist: bump2version; extra == "dev"
Dynamic: license-file
